odoo/addons/__init__.py
odoo/addons/crm_project_issue/__init__.py
odoo/addons/crm_project_issue/__manifest__.py
odoo/addons/crm_project_issue/i18n/af.po
odoo/addons/crm_project_issue/i18n/am.po
odoo/addons/crm_project_issue/i18n/ar.po
odoo/addons/crm_project_issue/i18n/bg.po
odoo/addons/crm_project_issue/i18n/bs.po
odoo/addons/crm_project_issue/i18n/ca.po
odoo/addons/crm_project_issue/i18n/cs.po
odoo/addons/crm_project_issue/i18n/da.po
odoo/addons/crm_project_issue/i18n/de.po
odoo/addons/crm_project_issue/i18n/el.po
odoo/addons/crm_project_issue/i18n/en_AU.po
odoo/addons/crm_project_issue/i18n/en_GB.po
odoo/addons/crm_project_issue/i18n/es.po
odoo/addons/crm_project_issue/i18n/es_AR.po
odoo/addons/crm_project_issue/i18n/es_BO.po
odoo/addons/crm_project_issue/i18n/es_CL.po
odoo/addons/crm_project_issue/i18n/es_CR.po
odoo/addons/crm_project_issue/i18n/es_DO.po
odoo/addons/crm_project_issue/i18n/es_EC.po
odoo/addons/crm_project_issue/i18n/es_PA.po
odoo/addons/crm_project_issue/i18n/es_PE.po
odoo/addons/crm_project_issue/i18n/es_PY.po
odoo/addons/crm_project_issue/i18n/es_VE.po
odoo/addons/crm_project_issue/i18n/et.po
odoo/addons/crm_project_issue/i18n/eu.po
odoo/addons/crm_project_issue/i18n/fa.po
odoo/addons/crm_project_issue/i18n/fi.po
odoo/addons/crm_project_issue/i18n/fo.po
odoo/addons/crm_project_issue/i18n/fr.po
odoo/addons/crm_project_issue/i18n/fr_BE.po
odoo/addons/crm_project_issue/i18n/fr_CA.po
odoo/addons/crm_project_issue/i18n/gl.po
odoo/addons/crm_project_issue/i18n/gu.po
odoo/addons/crm_project_issue/i18n/he.po
odoo/addons/crm_project_issue/i18n/hi.po
odoo/addons/crm_project_issue/i18n/hr.po
odoo/addons/crm_project_issue/i18n/hu.po
odoo/addons/crm_project_issue/i18n/hy.po
odoo/addons/crm_project_issue/i18n/id.po
odoo/addons/crm_project_issue/i18n/is.po
odoo/addons/crm_project_issue/i18n/it.po
odoo/addons/crm_project_issue/i18n/ja.po
odoo/addons/crm_project_issue/i18n/ka.po
odooku_odoo_project_issue-10.0.0.dist-info/DESCRIPTION.rst
odooku_odoo_project_issue-10.0.0.dist-info/METADATA
odooku_odoo_project_issue-10.0.0.dist-info/RECORD
odooku_odoo_project_issue-10.0.0.dist-info/WHEEL
odooku_odoo_project_issue-10.0.0.dist-info/metadata.json
odooku_odoo_project_issue-10.0.0.dist-info/top_level.txt
