Metadata-Version: 2.0
Name: odooku-odoo-project-issue
Version: 10.0.0
Summary: Odoo addons for the Issue Tracking app
Home-page: https://github.com/odooku/odooku-odoo
Author: Raymond Reggers - Adaptiv Design
Author-email: UNKNOWN
License: LGPLv3
Platform: UNKNOWN
Classifier: Intended Audience :: Developers
Classifier: Operating System :: OS Independent
Classifier: Programming Language :: Python
Classifier: Programming Language :: Python :: 2
Classifier: Programming Language :: Python :: 2.7
Classifier: License :: OSI Approved :: GNU Lesser General Public License v3 (LGPLv3)
Requires-Dist: odooku-odoo-base (==10.0.0)
Requires-Dist: odooku-odoo-mail (==10.0.0)
Requires-Dist: odooku-odoo-project (==10.0.0)
